frozen_data/__init__.py
frozen_data/apps.py
frozen_data/exceptions.py
frozen_data/fields.py
frozen_data/serializers.py
djang_frozen_data-0.1a1.dist-info/LICENSE
djang_frozen_data-0.1a1.dist-info/WHEEL
djang_frozen_data-0.1a1.dist-info/METADATA
djang_frozen_data-0.1a1.dist-info/RECORD
