Metadata-Version: 2.1
Name: djang-frozen-data
Version: 0.1a1
Summary: Django model field used to store snapshot of data.
Home-page: https://github.com/yunojuno/django-frozen-data
License: MIT
Author: YunoJuno
Author-email: code@yunojuno.com
Maintainer: YunoJuno
Maintainer-email: code@yunojuno.com
Requires-Python: >=3.9,<4.0
Classifier: Development Status :: 2 - Pre-Alpha
Classifier: Environment :: Web Environment
Classifier: Framework :: Django
Classifier: Framework :: Django :: 3.2
Classifier: License :: OSI Approved :: MIT License
Classifier: Operating System :: OS Independent
Classifier: Programming Language :: Python :: 3
Classifier: Programming Language :: Python :: 3 :: Only
Classifier: Programming Language :: Python :: 3.10
Classifier: Programming Language :: Python :: 3.9
Requires-Dist: django (>=3.2,<4.0)
Project-URL: Documentation, https://github.com/yunojuno/django-frozen-data
Project-URL: Repository, https://github.com/yunojuno/django-frozen-data
